nisystemlink/__init__.py
nisystemlink/clients/__init__.py
nisystemlink/clients/alarm/__init__.py
nisystemlink/clients/alarm/_alarm_client.py
nisystemlink/clients/alarm/models/__init__.py
nisystemlink/clients/alarm/models/_acknowledge_alarms_response.py
nisystemlink/clients/alarm/models/_alarm.py
nisystemlink/clients/alarm/models/_alarm_instances_partial_success.py
nisystemlink/clients/alarm/models/_create_or_update_alarm_request.py
nisystemlink/clients/alarm/models/_delete_alarms_response.py
nisystemlink/clients/alarm/models/_query_alarms_request.py
nisystemlink/clients/alarm/models/_query_alarms_response.py
nisystemlink/clients/artifact/__init__.py
nisystemlink/clients/artifact/_artifact_client.py
nisystemlink/clients/artifact/models/__init__.py
nisystemlink/clients/artifact/models/_upload_artifact_response.py
nisystemlink/clients/assetmanagement/__init__.py
nisystemlink/clients/assetmanagement/_asset_management_client.py
nisystemlink/clients/assetmanagement/models/__init__.py
nisystemlink/clients/assetmanagement/models/_asset.py
nisystemlink/clients/assetmanagement/models/_asset_calibration.py
nisystemlink/clients/assetmanagement/models/_asset_identification.py
nisystemlink/clients/assetmanagement/models/_asset_location.py
nisystemlink/clients/assetmanagement/models/_asset_types.py
nisystemlink/clients/assetmanagement/models/_asset_utilization_history_item.py
nisystemlink/clients/assetmanagement/models/_asset_utilization_history_response.py
nisystemlink/clients/assetmanagement/models/_create_asset_request.py
nisystemlink/clients/assetmanagement/models/_create_assets_partial_success_response.py
nisystemlink/clients/assetmanagement/models/_delete_assets_response.py
nisystemlink/clients/assetmanagement/models/_link_files_partial_success_response.py
nisystemlink/clients/assetmanagement/models/_query_asset_utilization_history_request.py
nisystemlink/clients/assetmanagement/models/_query_assets_request.py
nisystemlink_clients-2.29.1.dist-info/METADATA
nisystemlink_clients-2.29.1.dist-info/WHEEL
nisystemlink_clients-2.29.1.dist-info/licenses/LICENSE
nisystemlink_clients-2.29.1.dist-info/RECORD
