Metadata-Version: 2.4
Name: nisystemlink-clients
Version: 2.29.1
Summary: NI-SystemLink Python API
License: MIT
License-File: LICENSE
Keywords: nisystemlink,systemlink
Author: National Instruments
Maintainer: Richard Bell
Maintainer-email: richard.bell@emerson.com
Requires-Python: >=3.10,<4.0
Classifier: Development Status :: 5 - Production/Stable
Classifier: Intended Audience :: Developers
Classifier: Intended Audience :: Manufacturing
Classifier: Intended Audience :: Science/Research
Classifier: License :: OSI Approved :: MIT License
Classifier: Operating System :: Microsoft :: Windows
Classifier: Operating System :: POSIX
Classifier: Programming Language :: Python :: 3
Classifier: Programming Language :: Python :: 3.10
Classifier: Programming Language :: Python :: 3.11
Classifier: Programming Language :: Python :: 3.12
Classifier: Programming Language :: Python :: 3.13
Classifier: Programming Language :: Python :: 3.14
Classifier: Programming Language :: Python :: Implementation :: CPython
Classifier: Topic :: Scientific/Engineering
Classifier: Topic :: System :: Hardware
Provides-Extra: pyarrow
Requires-Dist: Events (>=0.4,<0.5)
Requires-Dist: aenum (>=3.1.11,<4.0.0)
Requires-Dist: httpx (>=0.28.1,<0.29.0)
Requires-Dist: pandas (>=2.1.0,<3.0.0)
Requires-Dist: pyarrow (>=21.0.0,<22.0.0) ; extra == "pyarrow"
Requires-Dist: pydantic (>=2.11.3,<3.0.0)
Requires-Dist: pyyaml (>=6.0.1,<7.0.0)
Requires-Dist: requests (>=2.28.1,<3.0.0)
Requires-Dist: uplink[pydantic] (>=0.10.0,<0.11.0)
